Workbook

Sheet Read Me
A1: Project Title: Silicior - Solar Finance Model: 10 MW Solar Farm
A2: Project Description: A 25-year project-finance model for a hypothetical 10 MW ground-mounted solar project located in Abu Dhabi, UAE, operating under a fixed-tariff Power Purchase Agreement (PPA).
A3: Key Assumptions:
A5: Capacity: 10 MW
A7: Total Project Cost: AED 400 million
A9: Debt/Equity Ratio: 70:30
A11: PPA Tariff: AED 0.275 / kWh
A13: Key Outputs:
A15: Equity IRR: 37.75%
A17: Author:
A19: Modeled by: Youssef Eleyouta

Sheet Assumptions
A3: Plant Capacity (MW) | B3: 10
A4: Capacity Utilization Factor (CUF) | B4: 0.22
A5: Capital Cost (CAPEX) per MW (AED) | B5: 40000000
A6: Annual OPEX (% of CAPEX) | B6: 0.01
A7: Annual OPEX Inflation | B7: 0.05
A8: Annual Degradation Rate | B8: 0.006
A9: PPA Tariff (AED per kWh) | B9: 0.275
A12: Debt : Equity Ratio | B12: 0.7
A13: Cost of Debt (Interest Rate) | B13: 0.095
A14: Loan Tenure (Years) | B14: 15
A15: Corporate Tax Rate | B15: 0.2517
A16: Depreciation Rate (WDV) | B16: 0.4
A18: Total CAPEX | B18: =B5*B3
A19: Total Debt Amount | B19: =B18*B12
A21: Equity IRR | B21: =IRR(Financials!B15:AA15)
A22: Discount Rate | B22: 0.1
A23: NPV | B23: =NPV(B22,Financials!C15:AA15)+Financials!B15
A24: Payback Period (Years) | B24: {=MATCH(TRUE,Financials!B16:AA16>0,0)-2}

Sheet Calculations
C2: 1 | D2: =C2+1 | E2: =D2+1 | F2: =E2+1 | G2: =F2+1 | H2: =G2+1 | I2: =H2+1 | J2: =I2+1 | K2: =J2+1 | ... Q2: =P2+1
B3: Year 0 | C3: Year 1 | D3: Year 2 | E3: Year 3 | F3: Year 4 | G3: Year 5 | H3: Year 6 | I3: Year 7 | J3: Year 8 | K3: Year 9 | L3: Year 10 | M3: Year 11 | N3: Year 12 | O3: Year 13 | P3: Year 14 | Q3: Year 15 | R3: Year 16 | S3: Year 17 | T3: Year 18 | U3: Year 19 | V3: Year 20 | W3: Year 21 | X3: Year 22 | Y3: Year 23 | Z3: Year 24 | AA3: Year 25
A5: Energy Generation (kWh) | C5: =Assumptions!$B$3 * 1000 * 24 * 365 * Assumptions!$B$4 | D5: =C5*(1-Assumptions!$B$8) | E5: =D5*(1-Assumptions!$B$8) | F5: =E5*(1-Assumptions!$B$8) | G5: =F5*(1-Assumptions!$B$8) | H5: =G5*(1-Assumptions!$B$8) | I5: =H5*(1-Assumptions!$B$8) | J5: =I5*(1-Assumptions!$B$8) | K5: =J5*(1-Assumptions!$B$8) | ... AA5: =Z5*(1-Assumptions!$B$8)
A6: Revenue | C6: =C5*Assumptions!$B$9 | D6: =D5*Assumptions!$B$9 | E6: =E5*Assumptions!$B$9 | F6: =F5*Assumptions!$B$9 | G6: =G5*Assumptions!$B$9 | H6: =H5*Assumptions!$B$9 | I6: =I5*Assumptions!$B$9 | J6: =J5*Assumptions!$B$9 | ... AA6: =AA5*Assumptions!$B$9
A8: Capital Expenditure (CAPEX) | B8: =Assumptions!$B$5*Assumptions!$B$3
A9: Operating Expenditure (OPEX) | C9: =B8*Assumptions!$B$6 | D9: =C9*(1+Assumptions!$B$7) | E9: =D9*(1+Assumptions!$B$7) | F9: =E9*(1+Assumptions!$B$7) | G9: =F9*(1+Assumptions!$B$7) | H9: =G9*(1+Assumptions!$B$7) | I9: =H9*(1+Assumptions!$B$7) | J9: =I9*(1+Assumptions!$B$7) | K9: =J9*(1+Assumptions!$B$7) | ... AA9: =Z9*(1+Assumptions!$B$7)
A11: Gross Block (Opening) | C11: =B13 | D11: =C13 | E11: =D13 | F11: =E13 | G11: =F13 | H11: =G13 | I11: =H13 | J11: =I13 | ... AA11: =Z13
A12: CAPEX Addition | B12: =B8
A13: Gross Block (Closing) | B13: =B11+B12 | C13: =C11+C12 | D13: =D11+D12 | E13: =E11+E12 | F13: =F11+F12 | G13: =G11+G12 | H13: =H11+H12 | I13: =I11+I12 | ... AA13: =AA11+AA12
A14: Depreciation | B14: =C13*Assumptions!$B$16 | C14: =C11*Assumptions!$B$16 | D14: =C15*Assumptions!$B$16 | E14: =D15*Assumptions!$B$16 | F14: =E15*Assumptions!$B$16 | G14: =F15*Assumptions!$B$16 | H14: =G15*Assumptions!$B$16 | I14: =H15*Assumptions!$B$16 | J14: =I15*Assumptions!$B$16 | K14: =J15*Assumptions!$B$16 | ... AA14: =Z15*Assumptions!$B$16
A15: Net Block (Closing) | B15: =C13-C14 | C15: =C11-C14 | D15: =C15-D14 | E15: =D15-E14 | F15: =E15-F14 | G15: =F15-G14 | H15: =G15-H14 | I15: =H15-I14 | J15: =I15-J14 | K15: =J15-K14 | ... AA15: =Z15-AA14
A17: Earnings Before Tax (EBT) | C17: =C6-C9-C14 | D17: =D6-D9-D14 | E17: =E6-E9-E14 | F17: =F6-F9-F14 | G17: =G6-G9-G14 | H17: =H6-H9-H14 | I17: =I6-I9-I14 | J17: =J6-J9-J14 | ... AA17: =AA6-AA9-AA14
A18: Taxes | C18: =MAX(0,C17)*Assumptions!$B$15 | D18: =MAX(0,D17)*Assumptions!$B$15 | E18: =MAX(0,E17)*Assumptions!$B$15 | F18: =MAX(0,F17)*Assumptions!$B$15 | G18: =MAX(0,G17)*Assumptions!$B$15 | H18: =MAX(0,H17)*Assumptions!$B$15 | I18: =MAX(0,I17)*Assumptions!$B$15 | J18: =MAX(0,J17)*Assumptions!$B$15 | ... AA18: =MAX(0,AA17)*Assumptions!$B$15
A20: Debt Drawdown | B20: =Assumptions!$B$19
A21: Opening Debt Balance | C21: =B24 | D21: =C24 | E21: =D24 | F21: =E24 | G21: =F24 | H21: =G24 | I21: =H24 | J21: =I24 | ... Q21: =P24
A22: Principal Repayment | C22: =-PPMT(Assumptions!$B$13, C2, Assumptions!$B$14, Assumptions!$B$19) | D22: =-PPMT(Assumptions!$B$13, D2, Assumptions!$B$14, Assumptions!$B$19) | E22: =-PPMT(Assumptions!$B$13, E2, Assumptions!$B$14, Assumptions!$B$19) | F22: =-PPMT(Assumptions!$B$13, F2, Assumptions!$B$14, Assumptions!$B$19) | G22: =-PPMT(Assumptions!$B$13, G2, Assumptions!$B$14, Assumptions!$B$19) | H22: =-PPMT(Assumptions!$B$13, H2, Assumptions!$B$14, Assumptions!$B$19) | I22: =-PPMT(Assumptions!$B$13, I2, Assumptions!$B$14, Assumptions!$B$19) | J22: =-PPMT(Assumptions!$B$13, J2, Assumptions!$B$14, Assumptions!$B$19) | ... Q22: =-PPMT(Assumptions!$B$13, Q2, Assumptions!$B$14, Assumptions!$B$19)
A23: Interest Paid | C23: =C21*Assumptions!$B$13 | D23: =D21*Assumptions!$B$13 | E23: =E21*Assumptions!$B$13 | F23: =F21*Assumptions!$B$13 | G23: =G21*Assumptions!$B$13 | H23: =H21*Assumptions!$B$13 | I23: =I21*Assumptions!$B$13 | J23: =J21*Assumptions!$B$13 | ... Q23: =Q21*Assumptions!$B$13
A24: Closing Debt Balance | B24: =B20 | C24: =C21-C22 | D24: =D21-D22 | E24: =E21-E22 | F24: =F21-F22 | G24: =G21-G22 | H24: =H21-H22 | I24: =I21-I22 | J24: =J21-J22 | ... Q24: =Q21-Q22

Sheet Financials
B3: Year 0 | C3: Year 1 | D3: Year 2 | E3: Year 3 | F3: Year 4 | G3: Year 5 | H3: Year 6 | I3: Year 7 | J3: Year 8 | K3: Year 9 | L3: Year 10 | M3: Year 11 | N3: Year 12 | O3: Year 13 | P3: Year 14 | Q3: Year 15 | R3: Year 16 | S3: Year 17 | T3: Year 18 | U3: Year 19 | V3: Year 20 | W3: Year 21 | X3: Year 22 | Y3: Year 23 | Z3: Year 24 | AA3: Year 25
A5: Revenue | C5: =Calculations!C6 | D5: =Calculations!D6 | E5: =Calculations!E6 | F5: =Calculations!F6 | G5: =Calculations!G6 | H5: =Calculations!H6 | I5: =Calculations!I6 | J5: =Calculations!J6 | ... AA5: =Calculations!AA6
A6: Operating Expenditure (OPEX) | C6: =Calculations!C9 | D6: =Calculations!D9 | E6: =Calculations!E9 | F6: =Calculations!F9 | G6: =Calculations!G9 | H6: =Calculations!H9 | I6: =Calculations!I9 | J6: =Calculations!J9 | ... AA6: =Calculations!AA9
A7: Depreciation | C7: =Calculations!C14 | D7: =Calculations!D14 | E7: =Calculations!E14 | F7: =Calculations!F14 | G7: =Calculations!G14 | H7: =Calculations!H14 | I7: =Calculations!I14 | J7: =Calculations!J14 | ... AA7: =Calculations!AA14
A8: Earnings Before Tax (EBT) | C8: =Calculations!C17 | D8: =Calculations!D17 | E8: =Calculations!E17 | F8: =Calculations!F17 | G8: =Calculations!G17 | H8: =Calculations!H17 | I8: =Calculations!I17 | J8: =Calculations!J17 | ... AA8: =Calculations!AA17
A9: Taxes | C9: =Calculations!C18 | D9: =Calculations!D18 | E9: =Calculations!E18 | F9: =Calculations!F18 | G9: =Calculations!G18 | H9: =Calculations!H18 | I9: =Calculations!I18 | J9: =Calculations!J18 | ... AA9: =Calculations!AA18
A10: Profit After Tax (PAT) | C10: =C8-C9 | D10: =D8-D9 | E10: =E8-E9 | F10: =F8-F9 | G10: =G8-G9 | H10: =H8-H9 | I10: =I8-I9 | J10: =J8-J9 | ... AA10: =AA8-AA9
A11: + Depreciation | C11: =Calculations!C14 | D11: =Calculations!D14 | E11: =Calculations!E14 | F11: =Calculations!F14 | G11: =Calculations!G14 | H11: =Calculations!H14 | I11: =Calculations!I14 | J11: =Calculations!J14 | ... AA11: =Calculations!AA14
A12: - Capital Expenditure (CAPEX) | C12: =-Calculations!B8 | D12: =-Calculations!C8 | E12: =-Calculations!D8 | F12: =-Calculations!E8 | G12: =-Calculations!F8 | H12: =-Calculations!G8 | I12: =-Calculations!H8 | J12: =-Calculations!I8 | ... AA12: =-Calculations!Z8
A13: + Debt Drawdown | C13: =Calculations!B20 | D13: =Calculations!C20 | E13: =Calculations!D20 | F13: =Calculations!E20 | G13: =Calculations!F20 | H13: =Calculations!G20 | I13: =Calculations!H20 | J13: =Calculations!I20 | ... AA13: =Calculations!Z20
A14: - Principal Repayment | C14: =-Calculations!C22 | D14: =-Calculations!D22 | E14: =-Calculations!E22 | F14: =-Calculations!F22 | G14: =-Calculations!G22 | H14: =-Calculations!H22 | I14: =-Calculations!I22 | J14: =-Calculations!J22 | ... Q14: =-Calculations!Q22
A15: '= Free Cash Flow to Equity (FCFE) | B15: =B10+SUM(B11:B14) | C15: =C10+SUM(C11:C14) | D15: =D10+SUM(D11:D14) | E15: =E10+SUM(E11:E14) | F15: =F10+SUM(F11:F14) | G15: =G10+SUM(G11:G14) | H15: =H10+SUM(H11:H14) | I15: =I10+SUM(I11:I14) | ... AA15: =AA10+SUM(AA11:AA14)
A16: Cumulative FCFE | B16: =B15 | C16: =B15+C15 | D16: =C15+D15 | E16: =D15+E15 | F16: =E15+F15 | G16: =F15+G15 | H16: =G15+H15 | I16: =H15+I15 | J16: =I15+J15 | ... AA16: =Z15+AA15

Sheet Power BI export
A1: Year | B1: Revenue | C1: OPEX | D1: PAT | E1: FCFE | F1: Closing Debt Balance | G1: Principal Repayment | H1: Interest Paid
A2: 0 | E2: {=TRANSPOSE(Financials!B15:AA15)} | F2: {=TRANSPOSE(Calculations!B24:AA24)}
A3: 1 | B3: {=TRANSPOSE(Financials!C5:AA5)} | C3: {=TRANSPOSE(Financials!C6:AA6)} | D3: {=TRANSPOSE(Financials!C10:AA10)} | E3: -80170235 | F3: 2.7083177e+08 | G3: {=TRANSPOSE(Calculations!C22:Q22)} | H3: {=TRANSPOSE(Calculations!C23:Q23)}
A4: =A3+1 | B4: 52680012 | C4: 4200000 | D4: -47519988 | E4: 38440795 | F4: 2.6079255e+08 | G4: 10039217 | H4: 25729018
A5: =A4+1 | B5: 52363932 | C5: 4410000 | D5: -9646068.1 | E5: 36960989 | F5: 2.4979961e+08 | G5: 10992942 | H5: 24775292
A6: =A5+1 | B6: 52049748 | C6: 4630500 | D6: 9622575.5 | E6: 32145303 | F6: 2.3776233e+08 | G6: 12037272 | H6: 23730963
A7: =A6+1 | B7: 51737450 | C7: 4862025 | D7: 19560132 | E7: 27115319 | F7: 2.2458152e+08 | G7: 13180813 | H7: 22587422
A8: =A7+1 | B8: 51427025 | C8: 5105126.2 | D8: 25352628 | E8: 23361238 | F8: 2.1014853e+08 | G8: 14432990 | H8: 21335245
A9: =A8+1 | B9: 51118463 | C9: 5360382.6 | D9: 28654742 | E9: 20315578 | F9: 1.9434441e+08 | G9: 15804124 | H9: 19964110
A10: =A9+1 | B10: 50811752 | C10: 5628401.7 | D10: 30459083 | E10: 17632544 | F10: 1.7703889e+08 | G10: 17305516 | H10: 18462719
A11: =A10+1 | B11: 50506882 | C11: 5909821.8 | D11: 31361009 | E11: 15098855 | F11: 1.5808935e+08 | G11: 18949540 | H11: 16818695
A12: =A11+1 | B12: 50203840 | C12: 6205312.9 | D12: 31717516 | E12: 12580201 | F12: 1.373396e+08 | G12: 20749746 | H12: 15018488
A13: =A12+1 | B13: 49902617 | C13: 6515578.5 | D13: 31742572 | E13: 9989058.4 | F13: 1.1461863e+08 | G13: 22720972 | H13: 13047262
A14: =A13+1 | B14: 49603202 | C14: 6841357.4 | D14: 31564318 | E14: 7265329.2 | F14: 89739168 | G14: 24879465 | H14: 10888770
A15: =A14+1 | B15: 49305582 | C15: 7183425.3 | D15: 31259388 | E15: 4364659.9 | F15: 62496154 | G15: 27243014 | H15: 8525221
... A17: =A16+1 | B17: 48715690 | C17: 7919726.4 | D17: 30433796 | E17: -2105875.7 | F17: -1.0058284e-07 | G17: 32665054 | H17: 3103180.2
A18: =A17+1 | B18: 48423396 | C18: 8315712.7 | D18: 29956285 | E18: 30031515 | F18: 0
A19: =A18+1 | B19: 48132856 | C19: 8731498.4 | D19: 29450259 | E19: 29495397 | F19: 0
A20: =A19+1 | B20: 47844059 | C20: 9168073.3 | D20: 28920974 | E20: 28948057 | F20: 0
A21: =A20+1 | B21: 47556994 | C21: 9626476.9 | D21: 28371247 | E21: 28387496 | F21: 0
A22: =A21+1 | B22: 47271652 | C22: 10107801 | D22: 27802414 | E22: 27812164 | F22: 0
A23: =A22+1 | B23: 46988023 | C23: 10613191 | D23: 27214909 | E23: 27220759 | F23: 0
A24: =A23+1 | B24: 46706094 | C24: 11143850 | D24: 26608601 | E24: 26612111 | F24: 0
A25: =A24+1 | B25: 46425858 | C25: 11701043 | D25: 25983003 | E25: 25985109 | F25: 0
A26: =A25+1 | B26: 46147303 | C26: 12286095 | D26: 25337396 | E26: 25338660 | F26: 0
A27: =A26+1 | B27: 45870419 | C27: 12900400 | D27: 24670898 | E27: 24671656 | F27: 0
